screenplay_pdf_to_json_storia/__init__.py
screenplay_pdf_to_json_storia/convert.py
screenplay_pdf_to_json_storia/parse_pdf/SortLines.py
screenplay_pdf_to_json_storia/parse_pdf/__init__.py
screenplay_pdf_to_json_storia/parse_pdf/cleanPage.py
screenplay_pdf_to_json_storia/parse_pdf/getTopTrends.py
screenplay_pdf_to_json_storia/parse_pdf/groupDualDialogues.py
screenplay_pdf_to_json_storia/parse_pdf/groupLines.py
screenplay_pdf_to_json_storia/parse_pdf/groupSections.py
screenplay_pdf_to_json_storia/parse_pdf/processInitialPages.py
screenplay_pdf_to_json_storia/parse_pdf/stitchSeperateWordsIntoLines.py
screenplay_pdf_to_json_storia/utils/__init__.py
screenplay_pdf_to_json_storia/utils/characterHelpers.py
screenplay_pdf_to_json_storia/utils/cleanScript.py
screenplay_pdf_to_json_storia/utils/headingHelpers.py
screenplay_pdf_to_json_storia/utils/transitionHelpers.py
screenplay_pdf_to_json_storia-0.1.0.dist-info/LICENSE.txt
screenplay_pdf_to_json_storia-0.1.0.dist-info/METADATA
screenplay_pdf_to_json_storia-0.1.0.dist-info/WHEEL
screenplay_pdf_to_json_storia-0.1.0.dist-info/RECORD
